tablip
