Metadata-Version: 2.1
Name: tablip
Version: 1.0.7
Summary: export data to file such as excel etc..
Home-page: https://github.com/bn0901/tablip
Author: bn.zheng
Author-email: zhengbingxian666@163.com
License: MIT Licence
Keywords: pip,tablip,featureextraction
Platform: any
